{
    "foodItems": [
        {
            "name": "Burger",
            "prepMethod": "grill",
            "prepTime": 14,
            "rotTime": 20,
            "disposeTime": 34,
            "ingredients": [
                {
                    "name": "Bun",
                    "minAmount": 10,
                    "maxAmount": 12
                },
                {
                    "name": "Patty",
                    "minAmount": 10,
                    "maxAmount": 12
                }
            ]
        },
        {
            "name": "Wrap",
            "prepMethod": "grill",
            "prepTime": 12,
            "rotTime": 18,
            "disposeTime": 30,
            "ingredients": [
                {
                    "name": "Tortilla",
                    "minAmount": 10,
                    "maxAmount": 12
                },
                {
                    "name": "Chicken",
                    "minAmount": 10,
                    "maxAmount": 12
                }
            ]
        },
        {
            "name": "Pizza",
            "prepMethod": "bake",
            "prepTime": 18,
            "rotTime": 24,
            "disposeTime": 42,
            "ingredients": [
                {
                    "name": "Dough",
                    "minAmount": 10,
                    "maxAmount": 12
                },
                {
                    "name": "Cheese",
                    "minAmount": 8,
                    "maxAmount": 12
                }
            ]
        },
        {
            "name": "Soup",
            "prepMethod": "boil",
            "prepTime": 16,
            "rotTime": 24,
            "disposeTime": 40,
            "ingredients": [
                {
                    "name": "Broth",
                    "minAmount": 10,
                    "maxAmount": 12
                },
                {
                    "name": "Carrot",
                    "minAmount": 5,
                    "maxAmount": 10
                }
            ]
        },
        {
            "name": "Sandwich",
            "prepMethod": "grill",
            "prepTime": 10,
            "rotTime": 16,
            "disposeTime": 26,
            "ingredients": [
                {
                    "name": "Bread",
                    "minAmount": 10,
                    "maxAmount": 12
                },
                {
                    "name": "Ham",
                    "minAmount": 10,
                    "maxAmount": 12
                }
            ]
        },
        {
            "name": "Fry Wrap",
            "prepMethod": "fry",
            "prepTime": 12,
            "rotTime": 18,
            "disposeTime": 30,
            "ingredients": [
                {
                    "name": "Tortilla",
                    "minAmount": 10,
                    "maxAmount": 12
                },
                {
                    "name": "Chicken",
                    "minAmount": 10,
                    "maxAmount": 12
                }
            ]
        },
        {
            "name": "Baked Wrap",
            "prepMethod": "bake",
            "prepTime": 12,
            "rotTime": 18,
            "disposeTime": 30,
            "ingredients": [
                {
                    "name": "Tortilla",
                    "minAmount": 10,
                    "maxAmount": 12
                },
                {
                    "name": "Cheese",
                    "minAmount": 8,
                    "maxAmount": 12
                }
            ]
        },
        {
            "name": "Deluxe Burger",
            "prepMethod": "grill",
            "prepTime": 14,
            "rotTime": 20,
            "disposeTime": 34,
            "ingredients": [
                {
                    "name": "Bun",
                    "minAmount": 10,
                    "maxAmount": 12
                },
                {
                    "name": "Patty",
                    "minAmount": 10,
                    "maxAmount": 12
                }
            ]
        },
        {
            "name": "Fried Pizza",
            "prepMethod": "fry",
            "prepTime": 12,
            "rotTime": 18,
            "disposeTime": 30,
            "ingredients": [
                {
                    "name": "Dough",
                    "minAmount": 10,
                    "maxAmount": 12
                },
                {
                    "name": "Cheese",
                    "minAmount": 8,
                    "maxAmount": 12
                }
            ]
        },
        {
            "name": "Boiled Sandwich",
            "prepMethod": "boil",
            "prepTime": 10,
            "rotTime": 16,
            "disposeTime": 26,
            "ingredients": [
                {
                    "name": "Bread",
                    "minAmount": 10,
                    "maxAmount": 12
                },
                {
                    "name": "Ham",
                    "minAmount": 10,
                    "maxAmount": 12
                }
            ]
        },
        {
            "name": "Grill Pizza",
            "prepMethod": "grill",
            "prepTime": 18,
            "rotTime": 24,
            "disposeTime": 42,
            "ingredients": [
                {
                    "name": "Dough",
                    "minAmount": 10,
                    "maxAmount": 12
                },
                {
                    "name": "Cheese",
                    "minAmount": 8,
                    "maxAmount": 12
                }
            ]
        }
    ],
    
    "trolls": [
        {
            "name": "Grug",
            "ingredients": [
                {
                    "name": "Bun",
                    "minAmount": 10,
                    "maxAmount": 12
                },
                {
                    "name": "Patty",
                    "minAmount": 10,
                    "maxAmount": 12
                }
            ]
        },
        {
            "name": "Snarg",
            "ingredients": [
                {
                    "name": "Tortilla",
                    "minAmount": 10,
                    "maxAmount": 12
                },
                {
                    "name": "Chicken",
                    "minAmount": 10,
                    "maxAmount": 12
                }
            ]
        },
        {
            "name": "Bork",
            "ingredients": [
                {
                    "name": "Dough",
                    "minAmount": 10,
                    "maxAmount": 12
                },
                {
                    "name": "Cheese",
                    "minAmount": 8,
                    "maxAmount": 12
                }
            ]
        },
        {
            "name": "Klog",
            "ingredients": [
                {
                    "name": "Tortilla",
                    "minAmount": 10,
                    "maxAmount": 12
                },
                {
                    "name": "Chicken",
                    "minAmount": 10,
                    "maxAmount": 12
                }
            ]
        },
        {
            "name": "Zorp",
            "ingredients": [
                {
                    "name": "Bread",
                    "minAmount": 10,
                    "maxAmount": 12
                },
                {
                    "name": "Ham",
                    "minAmount": 10,
                    "maxAmount": 12
                }
            ]
        },
        {
            "name": "Frim",
            "ingredients": [
                {
                    "name": "Broth",
                    "minAmount": 10,
                    "maxAmount": 12
                },
                {
                    "name": "Carrot",
                    "minAmount": 5,
                    "maxAmount": 10
                }
            ]
        },
        {
            "name": "Grimm",
            "ingredients": [
                {
                    "name": "Bread",
                    "minAmount": 10,
                    "maxAmount": 12
                },
                {
                    "name": "Ham",
                    "minAmount": 10,
                    "maxAmount": 12
                }
            ]
        }
    ]
}